README.rst
setup.cfg
setup.py
utools/__init__.py
utools/dates.py
utools/dicts.py
utools/files.py
utools/math.py
utools.egg-info/PKG-INFO
utools.egg-info/SOURCES.txt
utools.egg-info/dependency_links.txt
utools.egg-info/requires.txt
utools.egg-info/top_level.txt