Metadata-Version: 1.0
Name: utools
Version: 1.3
Summary: A set of useful functions to use for various purposes in any Python project
Home-page: http://github.com/julienc91/utools/
Author: Julien Chaumont
Author-email: utools@julienc.io
License: MIT
Platform: UNKNOWN
